mythologizer_postgres/__init__.py
mythologizer_postgres/benchmark.py
mythologizer_postgres/cli.py
mythologizer_postgres/db.py
mythologizer_postgres/schema.py
mythologizer_postgres/connectors/__init__.py
mythologizer_postgres/connectors/agent_attributes_def_store.py
mythologizer_postgres/connectors/myth_store.py
mythologizer_postgres/connectors/mytheme_store.py
mythologizer_postgres/connectors/mythicalgebra/__init__.py
mythologizer_postgres/connectors/mythicalgebra/mythic_algebra_connector.py
mythologizer_postgres-0.1.4.dist-info/licenses/LICENSE
mythologizer_postgres-0.1.4.dist-info/METADATA
mythologizer_postgres-0.1.4.dist-info/WHEEL
mythologizer_postgres-0.1.4.dist-info/entry_points.txt
mythologizer_postgres-0.1.4.dist-info/top_level.txt
mythologizer_postgres-0.1.4.dist-info/RECORD
