Metadata-Version: 2.4
Name: mythologizer_postgres
Version: 0.1.4
Summary: PostgreSQL database connector for mythology data with vector embeddings
Author-email: Pierre-Louis Suckrow <suckrowpierre@gmail.com>
License-Expression: MIT
Project-URL: Homepage, https://github.com/yourusername/mythologizerDB
Project-URL: Repository, https://github.com/yourusername/mythologizerDB
Project-URL: Documentation, https://github.com/yourusername/mythologizerDB#readme
Project-URL: Bug Tracker, https://github.com/yourusername/mythologizerDB/issues
Keywords: postgresql,vector,embeddings,mythology,sqlalchemy,pgvector
Classifier: Development Status :: 4 - Beta
Classifier: Intended Audience :: Developers
Classifier: Operating System :: OS Independent
Classifier: Programming Language :: Python :: 3
Classifier: Programming Language :: Python :: 3.13
Classifier: Topic :: Database
Classifier: Topic :: Scientific/Engineering :: Artificial Intelligence
Classifier: Topic :: Software Development :: Libraries :: Python Modules
Requires-Python: >=3.13
License-File: LICENSE
Requires-Dist: jinja2>=3.1.6
Requires-Dist: mythicalgebra>=0.1.0
Requires-Dist: numpy>=2.3.2
Requires-Dist: pgvector>=0.4.1
Requires-Dist: psycopg>=3.2.9
Requires-Dist: python-dotenv>=1.1.1
Requires-Dist: sqlalchemy>=2.0.42
Requires-Dist: typer>=0.16.0
Provides-Extra: test
Requires-Dist: pytest>=7.0.0; extra == "test"
Requires-Dist: pytest-cov>=4.0.0; extra == "test"
Requires-Dist: pytest-mock>=3.10.0; extra == "test"
Requires-Dist: pytest-xdist>=3.0.0; extra == "test"
Requires-Dist: pytest-asyncio>=0.23.0; extra == "test"
Requires-Dist: coverage>=7.0.0; extra == "test"
Provides-Extra: dev
Requires-Dist: pytest>=7.0.0; extra == "dev"
Requires-Dist: pytest-cov>=4.0.0; extra == "dev"
Requires-Dist: pytest-mock>=3.10.0; extra == "dev"
Requires-Dist: pytest-xdist>=3.0.0; extra == "dev"
Requires-Dist: pytest-asyncio>=0.23.0; extra == "dev"
Requires-Dist: coverage>=7.0.0; extra == "dev"
Requires-Dist: black>=23.0.0; extra == "dev"
Requires-Dist: isort>=5.12.0; extra == "dev"
Requires-Dist: flake8>=6.0.0; extra == "dev"
Requires-Dist: mypy>=1.0.0; extra == "dev"
Dynamic: license-file
